{
  "shortcode": "bih4",
  "name": "Comparing place value",
  "collectionId": 31,
  "level": 1,
  "sequence": 8,
  "yearGroups": [],
  "hasInterventions": false,
  "skills": [
    {
      "id": null,
      "name": "Comparing place value (one column apart)",
      "subjectArea": "",
      "prerequisites": []
    }
  ],
  "tags": [],
  "questions": [
    {
      "questionId": 158325,
      "imageURL": "https://images.diagnosticquestions.com/uploads/questions/863b3f38-afc3-458d-81ab-eb480a4ef8f9.jpg",
      "correctAnswer": "C",
      "explanations": {
        "A": "This statement is true. It means 90 x 10 = 900. Remember that when we multiply an integer by 10, we put a zero on the end of the integer.",
        "B": "This statement is true. It means 7 x 10 = 70. Remember that when we multiply an integer by 10, we put a zero on the end of the integer.",
        "C": "This statement is false. 10 x 500 = 5,000, not 50,000.",
        "D": "This statement is true. It means 800 x 10 = 8,000. Remember that when we multiply an integer by 10, we put a zero on the end of the integer."
      },
      "isCheckout": false
    },
    {
      "questionId": 158519,
      "imageURL": "https://images.diagnosticquestions.com/uploads/questions/1f2d65d9-d668-41c6-8a4c-ed0616474c3b.jpg",
      "correctAnswer": "B",
      "explanations": {
        "A": "This statement is true. It means 8 x 10 = 80. Remember that when we multiply an integer by 10, we put a zero on the end of the integer.",
        "B": "This statement is false. 10 x 60 = 600, not 6,000.",
        "C": "This statement is true. It means 4,000 x 10 = 40,000. Remember that when we multiply an integer by 10, we put a zero on the end of the integer.",
        "D": "This statement is true. It means 70 x 10 = 700. Remember that when we multiply an integer by 10, we put a zero on the end of the integer."
      },
      "isCheckout": true
    },
    {
      "questionId": 158326,
      "imageURL": "https://images.diagnosticquestions.com/uploads/questions/565acdd5-8a71-463e-863b-cc5df010fba8.jpg",
      "correctAnswer": "A",
      "explanations": {
        "A": "7500 ÷ 10 = 750. Therefore 750 is 1/10 of 7500.",
        "B": "I think you've added 10. But instead you need to find the missing number here: ? ÷ 10 = 750. Or, rearranging this: 750 x 10 = ?",
        "C": "I think you've divided by 100. But instead you need to find the missing number here: ? ÷ 10 = 750. Or, rearranging this: 750 x 10 = ?",
        "D": "I think you've divided by 10. But we're not finding 1/10 of 750. Instead, you need to find the missing number here: ? ÷ 10 = 750. Or, rearranging this: 750 x 10 = ?"
      },
      "isCheckout": false
    },
    {
      "questionId": 158520,
      "imageURL": "https://images.diagnosticquestions.com/uploads/questions/7f4def99-111d-412a-a970-5eae53dda5c9.jpg",
      "correctAnswer": "C",
      "explanations": {
        "A": "I think you've divided by 100. But instead you need to find the missing number here: ? ÷ 10 = 450. Or, rearranging this: 450 x 10 = ?",
        "B": "I think you've divided by 10. But we're not finding 1/10 of 450. Instead, you need to find the missing number here: ? ÷ 10 = 450. Or, rearranging this: 450 x 10 = ?",
        "C": "4500 ÷ 10 = 450. Therefore 450 is 1/10 of 4500.",
        "D": "I think you've added 10. But instead you need to find the missing number here: ? ÷ 10 = 450. Or, rearranging this: 450 x 10 = ?"
      },
      "isCheckout": true
    },
    {
      "questionId": 158327,
      "imageURL": "https://images.diagnosticquestions.com/uploads/questions/c715e5b7-8995-4c09-bf83-16928266902c.jpg",
      "correctAnswer": "B",
      "explanations": {
        "A": "You've chosen 9682, where the value of the 8 is 80. But you need to find the number where the value of the 8 is 800 (1/10 of 8000).",
        "B": "The value of 8 in 8,632.4 is 8000. 1/10 of 8000 = 800. The number where 8 has the value 800 is 7,836.",
        "C": "You've chosen 4632.8, where the value of the 8 is 8/10. But you need to find the number where the value of the 8 is 800 (1/10 of 8000).",
        "D": "You've chosen 86,324, where the value of the 8 is 80,000. But you need to find the number where the value of the 8 is 800 (1/10 of 8000)."
      },
      "isCheckout": false
    },
    {
      "questionId": 158521,
      "imageURL": "https://images.diagnosticquestions.com/uploads/questions/1b66850f-f754-4c71-a29b-ddd45971dd8a.jpg",
      "correctAnswer": "A",
      "explanations": {
        "A": "The value of 5 in 7,543.6 is 500. 1/10 of 500 = 50. The number where 5 has the value 50 is 9,652.",
        "B": "You've chosen 67,536, where the value of the 5 is 500, the same as the question. You need to find the number where the value of the 5 is 50 (1/10 of 500).",
        "C": "You've chosen 75,436, where the value of the 5 is 5,000. But you need to find the number where the value of the 5 is 50 (1/10 of 500).",
        "D": "You've chosen 632.5, where the value of the 5 is 5/10. But you need to find the number where the value of the 5 is 50 (1/10 of 500)."
      },
      "isCheckout": true
    },
    {
      "questionId": 158328,
      "imageURL": "https://images.diagnosticquestions.com/uploads/questions/ed534c63-475d-46c2-a68d-13f11b043d5e.jpg",
      "correctAnswer": "B",
      "explanations": {
        "A": "So that 42.1 becomes 1/10 of its size, we need to divide it by 10. Remember that dividing by 10 will make the number smaller.",
        "B": "42.1 ÷ 10 = 4.21. The decimal point has moved one place to the left.",
        "C": "So that 42.1 becomes 1/10 of its size, we need to divide it by 10. Remember that dividing by 10 will make the number smaller.",
        "D": "So that 42.1 becomes 1/10 of its size, we need to divide it by 10. Your answer would mean that we'd divided by 100 instead of 10."
      },
      "isCheckout": false
    },
    {
      "questionId": 158522,
      "imageURL": "https://images.diagnosticquestions.com/uploads/questions/4a2ba138-ab27-4e68-8c31-a203cd6f0bbf.jpg",
      "correctAnswer": "C",
      "explanations": {
        "A": "So that 685.1 becomes 1/10 of its size, we need to divide it by 10. Your answer would mean that we'd divided by 100 instead of 10.",
        "B": "So that 685.1 becomes 1/10 of its size, we need to divide it by 10. Remember that dividing by 10 will make the number smaller.",
        "C": "685.1 ÷ 10 = 68.51. The decimal point has moved one place to the left.",
        "D": "So that 685.1 becomes 1/10 of its size, we need to divide it by 10. Remember that dividing by 10 will make the number smaller."
      },
      "isCheckout": true
    },
    {
      "questionId": 158329,
      "imageURL": "https://images.diagnosticquestions.com/uploads/questions/f873cba4-cec0-44bb-a48f-19a8112519e1.jpg",
      "correctAnswer": "C",
      "explanations": {
        "A": "0.016 is ten times smaller than 0.16, we want to calculate the number that is ten times bigger than 0.16.",
        "B": "I think you've added 10. But instead you need to multiply by 10, to make 0.16 ten times bigger.",
        "C": "To find the number ten times bigger than 0.16, we multiply by 10. 0.16 x 10 = 1.6.",
        "D": "16 is one hundred times bigger than 0.16, but we want to calculate the number that is ten times bigger than 0.16."
      },
      "isCheckout": false
    },
    {
      "questionId": 158523,
      "imageURL": "https://images.diagnosticquestions.com/uploads/questions/c506dae8-14c4-44a1-b342-58d0d0dc88fa.jpg",
      "correctAnswer": "B",
      "explanations": {
        "A": "I think you've added 10. But instead you need to multiply by 10, to make 0.24 ten times bigger...",
        "B": "To find the number ten times bigger than 0.24, we multiply by 10. 0.24 x 10 = 2.4",
        "C": "24 is one hundred times bigger than 0.24, but we want to calculate the number that is ten times bigger than 0.24...",
        "D": "0.024 is ten times smaller than 0.24, we want to calculate the number that is ten times bigger than 0.24..."
      },
      "isCheckout": true
    }
  ],
  "categories": []
}