{
  "shortcode": "bij3",
  "name": "Problem solving with customary units",
  "collectionId": 31,
  "level": 1,
  "sequence": 86,
  "yearGroups": [],
  "hasInterventions": false,
  "skills": [
    {
      "id": null,
      "name": "Solving problems involving customary units of weight",
      "subjectArea": "",
      "prerequisites": []
    },
    {
      "id": null,
      "name": "Solving problems involving customary units of length",
      "subjectArea": "",
      "prerequisites": []
    },
    {
      "id": null,
      "name": "Solving problems involving customary units of capacity",
      "subjectArea": "",
      "prerequisites": []
    }
  ],
  "tags": [],
  "questions": [
    {
      "questionId": 158440,
      "imageURL": "https://images.diagnosticquestions.com/uploads/questions/791905dc-aaea-4bd7-83c1-50eae71c0412.jpg",
      "correctAnswer": "A",
      "explanations": {
        "A": "This is the correct answer in pounds, now convert this into ounces.",
        "B": "30 ÷ 5 = 6. Therefore, there will be 6 pounds in every bag. 1 pound = 16 ounces. So, in ounces, 6 pounds = 6 x 16 = 96 ounces.",
        "C": "I think you've used 10 ounces = 1 pound, but remember that 1 pound = 16 ounces.",
        "D": "In the first step, I think you multiplied 30 by 5. But, Prim is sharing the sand, which means we need to divide."
      },
      "isCheckout": false
    },
    {
      "questionId": 158639,
      "imageURL": "https://images.diagnosticquestions.com/uploads/questions/d8aa4a26-25c2-4f71-9559-fe08189c34d7.jpg",
      "correctAnswer": "C",
      "explanations": {
        "A": "I think you've used 10 ounces = 1 pound, but remember that 1 pound = 16 ounces.",
        "B": "In the first step, I think you multiplied 28 by 4. But, Paulina is sharing the sand, which means we need to divide.",
        "C": "This is the correct answer in pounds, now convert this into ounces.",
        "D": "28 ÷ 4 = 7. Therefore, there will be 7 pounds in every bag. 1 pound = 16 ounces. So, in ounces, 7 pounds = 7 x 16 = 112 ounces."
      },
      "isCheckout": true
    },
    {
      "questionId": 158441,
      "imageURL": "https://images.diagnosticquestions.com/uploads/questions/191d971a-ddd9-4cef-843c-2a3fe949ceca.jpg",
      "correctAnswer": "D",
      "explanations": {
        "A": "I think you've calculated the flour left in the bag after 1 cake was made. How much flour is left after all 3 cakes have been made?",
        "B": "I think you thought there was just one pound of flour in the bag. The bag contains 2 pounds. How many ounces is this?",
        "C": "I think you've compared the amount needed to make one cake with a one pound bag of flour. Remember you are making three cakes, and have 2 pounds of flour in the bag.",
        "D": "6 x 3 = 18 ozs used for the 3 cakes. The bag of flour weighs 2 pounds, 1 pound = 16 ounces, so the bag of flour weighs 2 x 16 = 32 ounces. 32 - 18 = 14. Therefore, 14 ounces of flour are left in the bag."
      },
      "isCheckout": false
    },
    {
      "questionId": 158640,
      "imageURL": "https://images.diagnosticquestions.com/uploads/questions/959a014e-6e4c-4cf7-adca-099a9769d5c0.jpg",
      "correctAnswer": "C",
      "explanations": {
        "A": "I think you've calculated the flour left in the bag after 1 cake was made. How much flour is left after all 5 cakes have been made?",
        "B": "I think you thought there was just one pound of flour in the bag. The bag contains 6 pounds. How many ounces is this?",
        "C": "8 x 5 = 40 ozs used for the 5 cakes. The bag of flour weighs 6 pounds, 1 pound = 16 ounces, so the bag of flour weighs 6 x 16 = 96 ounces. 96 - 40 = 56. Therefore, 56 ounces of flour are left in the bag.",
        "D": "I think you've compared the amount needed to make one cake with a one pound bag of flour. Remember you are making five cakes, and have 6 pounds of flour in the bag."
      },
      "isCheckout": true
    },
    {
      "questionId": 158442,
      "imageURL": "https://images.diagnosticquestions.com/uploads/questions/7e9ca475-1859-4080-aa0e-c893c1ee2990.jpg",
      "correctAnswer": "A",
      "explanations": {
        "A": "This is the correct answer in feet, now convert this into yards.",
        "B": "To make 12 gift bags, Raj will need 12 x 1.4 feet of fabric = 16.8 feet. 3 feet = 1 yard, therefore to convert 16.8 feet into yards: 16.8 ÷ 3 = 5.6 yards.",
        "C": "I think you multiplied when converting from feet to yards, But, when converting from feet to yards, 3 feet = 1 yard, so we divide the number of feet by 3.",
        "D": "I think you've added the numbers in the question. But, instead, first you need to calculate the total number of feet of fabric that Raj needs. This will be a multiplication sum. Then, use the following conversion fact, to give the answer in yards: 3 feet = 1 yard."
      },
      "isCheckout": false
    },
    {
      "questionId": 158641,
      "imageURL": "https://images.diagnosticquestions.com/uploads/questions/3e9d1a81-6a5d-4156-bb76-2964ba4896cf.jpg",
      "correctAnswer": "A",
      "explanations": {
        "A": "This is the correct answer in feet, now convert this into yards.",
        "B": "I think you multiplied when converting from feet to yards, But, when converting from feet to yards, 3 feet = 1 yard, so we divide the number of feet by 3.",
        "C": "To make 7 gift bags, Faizan will need 7 x 2.1 feet of fabric = 14.7 feet. 3 feet = 1 yard, therefore to convert 14.7 feet into yards: 14.7 ÷ 3 = 4.9 yards.",
        "D": "I think you've added the numbers in the question. But, instead, first you need to calculate the total number of feet of fabric that Faizan needs. This will be a multiplication sum. Then, use the following conversion fact, to give the answer in yards: 3 feet = 1 yard."
      },
      "isCheckout": true
    },
    {
      "questionId": 158443,
      "imageURL": "https://images.diagnosticquestions.com/uploads/questions/f30df2a8-87f9-4dac-a33e-584a0602376b.jpg",
      "correctAnswer": "C",
      "explanations": {
        "A": "I think you've given the weight of just 2 of the bikes, in pounds. There are 20 road bikes and 10 mountain bike. Calculate the total weight of these bikes, in pounds. And then convert this mass to tons.",
        "B": "This is the correct answer in pounds, now convert this into tons",
        "C": "The twenty road bikes weigh a total of (20x19) 380 pounds. The mountain bikes weigh (10 x 32) 320 pounds. This is 700 pounds in total. Converting this to tons, 1 ton = 2000 pounds, so 700 pounds = (700 ÷ 2000) tons = 0.35 tons",
        "D": "I think you have divided by 1000, but remember there are 2000 pounds in a ton."
      },
      "isCheckout": false
    },
    {
      "questionId": 158642,
      "imageURL": "https://images.diagnosticquestions.com/uploads/questions/00949367-215c-4d79-883f-ad88a3d5bec0.jpg",
      "correctAnswer": "D",
      "explanations": {
        "A": "I think you have divided by 1000, but remember there are 2000 pounds in a ton.",
        "B": "This is the correct answer in pounds, now convert this into tons.",
        "C": "I think you've given the weight of just 2 of the bikes, in pounds. There are 30 road bikes and 20 mountain bikes. Calculate the total weight of these bikes, in pounds. And then convert this mass to tons.",
        "D": "The thirty road bikes weigh a total of (30x21) 630 pounds. The mountain bikes weigh (20 x 28) 560 pounds. This is 1190 pounds in total. Converting this to tons, 1 ton = 2000 pounds, so 1190 pounds = (1190 ÷ 2000) tons = 0.595 tons"
      },
      "isCheckout": true
    },
    {
      "questionId": 158444,
      "imageURL": "https://images.diagnosticquestions.com/uploads/questions/439af71a-3f9c-401e-85eb-c7245bd216d2.jpg",
      "correctAnswer": "A",
      "explanations": {
        "A": "This would be the correct answer if it was 1 ounce of flour for every cup of liquid. But, instead, it's 1 ounce of flour for every pint of liquid. So, first convert 5 cups to pints.",
        "B": "Ted uses a total of 5 cups of liquid in the stew. 1 cup = 1/2 pint, therefore, 5 cups = (5 x 1/2) pints = 2.5 pints. Therefore, Ted needs 2.5 ounces of flour.",
        "C": "This would be correct if 1 cup was equal to 2 pints, but that is not true. The conversion fact is that 1 cup = 1/2 pint.",
        "D": "I think you've assumed that 1 cup is equal to 1/4 pint, but that is not true. The conversion fact is that 1 cup = 1/2 pint."
      },
      "isCheckout": false
    },
    {
      "questionId": 158643,
      "imageURL": "https://images.diagnosticquestions.com/uploads/questions/9de2f2b2-1aff-4dee-b6e8-748fe2bf6783.jpg",
      "correctAnswer": "B",
      "explanations": {
        "A": "Leo uses a total of 8 cups of liquid in the stew. 1 cup = 1/2 pint, therefore, 8 cups = (8 x 1/2) pints = 4 pints. Therefore, Leo needs 4 ounces of flour.",
        "B": "This would be the correct answer if it was 1 ounce of flour for every cup of liquid. But, instead, it's 1 ounce of flour for every pint of liquid. So, first convert 8 cups to pints.",
        "C": "I think you've assumed that 1 cup is equal to 1/4 pint, but that is not true. The conversion fact is that 1 cup = 1/2 pint.",
        "D": "This would be correct if 1 cup was equal to 2 pints, but that is not true. The conversion fact is that 1 cup = 1/2 pint."
      },
      "isCheckout": true
    }
  ],
  "categories": []
}