{
  "shortcode": "bitc",
  "name": "Multiplication laws",
  "collectionId": 33,
  "level": 1,
  "sequence": 5,
  "yearGroups": [],
  "hasInterventions": false,
  "skills": [
    {
      "id": null,
      "name": "Understand the commutativity of multiplication",
      "subjectArea": "",
      "prerequisites": []
    },
    {
      "id": null,
      "name": "Understand the non-commutativity of division",
      "subjectArea": "",
      "prerequisites": []
    },
    {
      "id": null,
      "name": "Recognise and use the law of distributivity",
      "subjectArea": "",
      "prerequisites": []
    },
    {
      "id": null,
      "name": "Mental multiplication and the laws of arithmetic",
      "subjectArea": "",
      "prerequisites": []
    }
  ],
  "tags": [],
  "questions": [
    {
      "questionId": 89263,
      "imageURL": "https://images.diagnosticquestions.com/uploads/questions/1cfadf83-6100-44cb-b08d-b429e94ecb8e.jpg",
      "correctAnswer": "A",
      "explanations": {
        "A": "If you try this with numbers it may be easier to see. For example: 6 × 3 = 3 × 6 = 18, so that works. 6 ÷ 3 = 2 but 3 ÷ 6 = ½, so numbers have to be in the correct position for division.",
        "B": "I think that you have not recognised that division is non-commutative, which means we cannot switch the 𝑎 and 𝑏 around.",
        "C": "I think that you have not recognised that division is non-commutative, which means we cannot switch the 𝑎 and 𝑏 around.",
        "D": "I think that you have not recognised that division is non-commutative, which means we cannot switch the 𝑎 and 𝑏 around, but multiplication is commutative."
      },
      "isCheckout": false
    },
    {
      "questionId": 89276,
      "imageURL": "https://images.diagnosticquestions.com/uploads/questions/2e95dfe8-5679-495e-89f3-82fe084c0bff.jpg",
      "correctAnswer": "A",
      "explanations": {
        "A": "If you try this with numbers it may be easier to see. For example: 6 ＋ 1 = 1 ＋ 6 = 7, so that works. 6 − 1 = 5 but 1 − 6 = −5, so numbers have to be in the correct position for subtraction.",
        "B": "I think that you have not recognised that subtraction is non-commutative, which means we cannot switch the 𝑎 and 𝑏 around.",
        "C": "I think that you have not recognised that subtraction is non-commutative, which means we cannot switch the 𝑎 and 𝑏 around.",
        "D": "I think that you have not recognised that subtraction is non-commutative, which means we cannot switch the 𝑎 and 𝑏 around, but addition is commutative."
      },
      "isCheckout": true
    },
    {
      "questionId": 89264,
      "imageURL": "https://images.diagnosticquestions.com/uploads/questions/c05234ef-7c5d-48de-b6d5-d6908cc3b300.jpg",
      "correctAnswer": "A",
      "explanations": {
        "A": "The law of commutativity says you can swap numbers around and still get the same answer. This law applies when you multiply.",
        "B": "I think that you may be confused with factor pairs.",
        "C": "I think that you may be confusing associativity and commutativity.",
        "D": "I think that you may be confusing distributivity and commutativity."
      },
      "isCheckout": false
    },
    {
      "questionId": 89277,
      "imageURL": "https://images.diagnosticquestions.com/uploads/questions/b950f62b-46d1-4751-b933-27d150c2abb6.jpg",
      "correctAnswer": "A",
      "explanations": {
        "A": "I think that you may be confusing associativity and commutativity.",
        "B": "The law of commutativity says you can swap numbers around and still get the same answer. This law applies when you add.",
        "C": "I think that you may be confusing distributivity and commutativity.",
        "D": "I think that you may be confused with factor pairs."
      },
      "isCheckout": true
    },
    {
      "questionId": 89268,
      "imageURL": "https://images.diagnosticquestions.com/uploads/questions/fc791c8c-6f84-4645-b71d-cfb2af709c4c.jpg",
      "correctAnswer": "A",
      "explanations": {
        "A": "25 ✕ 14 = 25 ✕ (2 ✕ ★). The 25 appears on both sides. The 14 is now represented as 2 ✕ ★. Therefore, we know that 14 = 2 ✕ ★ which means that ★ must have a value of 7.",
        "B": "I think you might have missed the '2 ✕' in the brackets.",
        "C": "I think you might have used subtraction instead of division when solving 14 = 2 ✕ ★.",
        "D": "I think you might have used multiplication instead of division when solving 14 = 2 ✕ ★"
      },
      "isCheckout": false
    },
    {
      "questionId": 89281,
      "imageURL": "https://images.diagnosticquestions.com/uploads/questions/3418e564-ce8f-44ba-be13-191cf21b5ef4.jpg",
      "correctAnswer": "C",
      "explanations": {
        "A": "I think you might have used subtraction instead of division when solving 12 = 4 ✕ ★.",
        "B": "I think you might have missed the '4 ✕' in the brackets.",
        "C": "15 ✕ 12 = 15 ✕ (4 ✕ ★). The 15 appears on both sides. The 12 is now represented as 4 ✕ ★. Therefore, we know that 12 = 4 ✕ ★ which means that ★ must have a value of 3.",
        "D": "I think you might have solved this step incorrectly: 12 = 4 ✕ ★."
      },
      "isCheckout": true
    },
    {
      "questionId": 89287,
      "imageURL": "https://images.diagnosticquestions.com/uploads/questions/f940ecd4-1818-4712-b5f8-3658619396ab.jpg",
      "correctAnswer": "D",
      "explanations": {
        "A": "Not quite. Commutativity describes how, in addition and multiplication, you can swap the numbers around and still get the same answer. For example: 7 ✕ 9 = 9 ✕ 7.",
        "B": "Not quite. 5 and 2 are not factors of 7, 5 ✕ 2 = 10 NOT 7",
        "C": "Not quite. Associativity describes how, in addition and multiplication, you can change the order in which you choose to add or multiply. For example: (7 x 3) x 3 = 7 x (3 x 3)",
        "D": "Distributivity describes how multiplying a group of numbers added together is the same as multiplying the numbers separately before finding the sum. For example 7 lots of 9 is the same as adding 5 lots of 9 to 2 lots of 9. As shown here."
      },
      "isCheckout": false
    },
    {
      "questionId": 89300,
      "imageURL": "https://images.diagnosticquestions.com/uploads/questions/06170b2a-6118-440e-9d13-09da9d57927b.jpg",
      "correctAnswer": "C",
      "explanations": {
        "A": "Not quite. Associativity describes how, in addition and multiplication, you can change the order of which you choose to add or multiply. For example: (8 x 2) x 4 = 8 x (2 x 4)",
        "B": "Not quite. Commutativity describes how, in addition and multiplication, you can swap the numbers around and still get the same answer. For example: 8 ✕ 4 = 4 ✕ 8.",
        "C": "Distributivity describes how multiplying a group of numbers added together is the same as multiplying the numbers separately before finding the sum. For example 8 lots of 4 is the same as adding 5 lots of 4 to 3 lots of 4. As shown here.",
        "D": "Not quite. 5 and 3 are not factors of 8, 5 ✕ 3 = 15 NOT 8"
      },
      "isCheckout": true
    },
    {
      "questionId": 146170,
      "imageURL": "https://images.diagnosticquestions.com/uploads/questions/47378b38-ffa0-4d01-91b9-53bf1a7e8c05.jpg",
      "correctAnswer": "D",
      "explanations": {
        "A": "Almost, just don't forget to take into account the place value of the 4. It's not worth 4 as it isn't in the units column",
        "B": "Almost, just make sure you are multiplying and adding in the correct places.",
        "C": "Almost. Just check the totals here",
        "D": "We multiply the tens by 3, then the units by 3, and then add the totals together."
      },
      "isCheckout": false
    },
    {
      "questionId": 146190,
      "imageURL": "https://images.diagnosticquestions.com/uploads/questions/57bfc627-12b2-438f-84a7-08429e6e65c4.jpg",
      "correctAnswer": "A",
      "explanations": {
        "A": "We multiply the tens by 3, then the units by 3, and then add the totals together.",
        "B": "Almost, just make sure you are multiplying and adding in the correct places.",
        "C": "Almost. Just check the totals here",
        "D": "Almost, just don't forget to take into account the place value of the 5. It's not worth 5 as it isn't in the units column"
      },
      "isCheckout": true
    }
  ],
  "categories": []
}