{
  "shortcode": "vx9",
  "name": "Probability - method selection 1",
  "collectionId": 24,
  "level": 1,
  "sequence": 251,
  "yearGroups": [],
  "hasInterventions": false,
  "skills": [
    {
      "id": null,
      "name": "Calculate the whole amount, given a fraction of the amount",
      "subjectArea": "",
      "prerequisites": []
    },
    {
      "id": null,
      "name": "Know that probabilities must lie between 0, impossible, and 1, certain",
      "subjectArea": "",
      "prerequisites": []
    },
    {
      "id": null,
      "name": "Assign probabilities to single events using fractions",
      "subjectArea": "",
      "prerequisites": []
    },
    {
      "id": null,
      "name": "Calculate the probability of two independent events occurring without drawing a tree diagram",
      "subjectArea": "",
      "prerequisites": []
    },
    {
      "id": null,
      "name": "Calculate the probability of two dependent events occurring without drawing a tree diagram",
      "subjectArea": "",
      "prerequisites": []
    }
  ],
  "tags": [],
  "questions": [
    {
      "questionId": 109520,
      "imageURL": "https://images.diagnosticquestions.com/uploads/questions/5afb6e05-d8d0-41c2-8350-46a0a1af4215.jpg",
      "correctAnswer": "A",
      "explanations": {
        "A": "Tom is correct. Any event with a probability of 0 is impossible. Katie is wrong, as a probability of one means that an event is certain to happen.",
        "B": "Not quite. Remember that probability lies between 0 and 1",
        "C": "Not quite. Remember that probability lies between 0 and 1",
        "D": "At least one person is correct. Remember that probability lies between 0 and 1"
      },
      "isCheckout": false
    },
    {
      "questionId": 109530,
      "imageURL": "https://images.diagnosticquestions.com/uploads/questions/36ee32cb-d54a-4e36-bb4e-15c86e4dc6e0.jpg",
      "correctAnswer": "C",
      "explanations": {
        "A": "Almost. Remember that probability lies between 0 and 1",
        "B": "Almost. Remember that probability lies between 0 and 1",
        "C": "If an event has probability 1 it is certain to happen, and if it has probability 0, it is impossible.",
        "D": "Not quite, at least one person is correct. Remember that probability lies between 0 and 1"
      },
      "isCheckout": true
    },
    {
      "questionId": 109521,
      "imageURL": "https://images.diagnosticquestions.com/uploads/questions/4ecf18f3-ebd6-498a-9889-037e39aa8bc9.jpg",
      "correctAnswer": "D",
      "explanations": {
        "A": "Almost. Remember the denominator needs to be the total number of possible outcomes",
        "B": "You are really close. Can you have a probability greater than 1?",
        "C": "Almost, this is the probability of picking a yellow ball",
        "D": "There are 4 red balls and 7 in total, so the probability is 4/7."
      },
      "isCheckout": false
    },
    {
      "questionId": 109531,
      "imageURL": "https://images.diagnosticquestions.com/uploads/questions/ffb2f446-0f75-48c3-bd05-5f0304cb5643.jpg",
      "correctAnswer": "B",
      "explanations": {
        "A": "Almost. Remember the denominator needs to be the total number of possible outcomes",
        "B": "There are 5 red balls and 9 in total, so the probability is 5/9.",
        "C": "You are really close. Can you have a probability greater than 1?",
        "D": "Almost, this is the probability of picking a yellow ball"
      },
      "isCheckout": true
    },
    {
      "questionId": 109522,
      "imageURL": "https://images.diagnosticquestions.com/uploads/questions/b70224a5-552d-41f7-9307-c4abec049547.jpg",
      "correctAnswer": "B",
      "explanations": {
        "A": "Not quite. The 3 yellow balls need to represent 1/3 of all the balls, so 1/3 = 3. Think about the fraction that would be red, and how many more reds you need.",
        "B": "Adding 2 red balls means that there will be 3 yellow balls out of a total of 9, and so the probability is 3/9 = ⅓",
        "C": "Not quite. The 3 yellow balls need to represent 1/3 of all the balls, so 1/3 = 3. Think about the fraction that would be red, and how many more reds you need.",
        "D": "Not quite. The 3 yellow balls need to represent 1/3 of all the balls, so 1/3 = 3. Think about the fraction that would be red, and how many more reds you need."
      },
      "isCheckout": false
    },
    {
      "questionId": 109532,
      "imageURL": "https://images.diagnosticquestions.com/uploads/questions/11622f3f-6d91-46c0-a77d-c67838538f7c.jpg",
      "correctAnswer": "C",
      "explanations": {
        "A": "Not quite. The 4 yellow balls need to represent 1/3 of all the balls, so 1/3 = 4. Think about the fraction that would be red, and how many more reds you need.",
        "B": "Not quite. The 4 yellow balls need to represent 1/3 of all the balls, so 1/3 = 4. Think about the fraction that would be red, and how many more reds you need.",
        "C": "Adding 3 red balls means that there will be 4 yellow balls out of a total of 12, and so the probability is 4/12 = ⅓",
        "D": "Not quite. The 4 yellow balls need to represent 1/3 of all the balls, so 1/3 = 4. Think about the fraction that would be red, and how many more reds you need."
      },
      "isCheckout": true
    },
    {
      "questionId": 109523,
      "imageURL": "https://images.diagnosticquestions.com/uploads/questions/154412f6-5867-43c7-b0e7-ff330845a7bc.jpg",
      "correctAnswer": "A",
      "explanations": {
        "A": "If she puts the yellow ball back, the number of yellow balls will remain as three. Dividing by the total (7) gives the probability.",
        "B": "I think you assumed she didn't put the ball back in so the number of balls has decreased. As it was replaced the number of balls is unchanged.",
        "C": "I think you assumed she didn't put the yellow ball back in so the number of yellow balls has decreased. As it was replaced the number of yellow balls is unchanged.",
        "D": "I think you assumed she didn't put the yellow ball back in so the number of yellow balls and the total balls has decreased. As it was replaced the number of balls is unchanged."
      },
      "isCheckout": false
    },
    {
      "questionId": 109533,
      "imageURL": "https://images.diagnosticquestions.com/uploads/questions/8ff7c97b-0d64-42e0-af21-5bd992ba57a7.jpg",
      "correctAnswer": "B",
      "explanations": {
        "A": "I think you assumed she didn't put the yellow ball back in so the number of yellow balls and the total balls has decreased. As it was replaced the number of balls is unchanged.",
        "B": "If she puts the yellow ball back, the number of yellow balls will remain as four. Dividing by the total (9) gives the probability.",
        "C": "I think you assumed she didn't put the ball back in so the number of balls has decreased. As it was replaced the number of balls is unchanged.",
        "D": "I think you assumed she didn't put the yellow ball back in so the number of yellow balls has decreased. As it was replaced the number of yellow balls is unchanged."
      },
      "isCheckout": true
    },
    {
      "questionId": 109524,
      "imageURL": "https://images.diagnosticquestions.com/uploads/questions/ba6de0b2-ff79-429e-acf5-6f75a4de8fe9.jpg",
      "correctAnswer": "D",
      "explanations": {
        "A": "I think you assumed she put the ball back, but she kept the yellow ball she picked. Think about how many yellow balls are now in the cup, and how many balls there will be in total.",
        "B": "I think that you saw that the number of balls will decrease as she didn't replace it. Think about how many yellow balls are now in the cup.",
        "C": "I think that you saw that the number of yellow balls will decrease as she didn't replace it. Think about how many balls are now in the cup.",
        "D": "Removing one yellow ball means that there will be 2 remaining out of a total of 6, so the probability is 2/6."
      },
      "isCheckout": false
    },
    {
      "questionId": 109534,
      "imageURL": "https://images.diagnosticquestions.com/uploads/questions/ffee92c8-23a2-4d61-b281-677c3d753f12.jpg",
      "correctAnswer": "B",
      "explanations": {
        "A": "I think you assumed she put the ball back, but she kept the yellow ball she picked. Think about how many yellow balls are now in the cup, and how many balls there will be in total",
        "B": "Removing one yellow ball means that there will be 3 left out of a total of 8, so the probability is 3/8.",
        "C": "I think that you saw that the number of balls will decrease as she didn't replace it. Think about how many yellow balls are now in the cup.",
        "D": "I think that you saw that the number of yellow balls will decrease as she didn't replace it. Think about how many balls are now in the cup."
      },
      "isCheckout": true
    }
  ],
  "categories": []
}